{
  "version": 1,
  "files": {
    "memory/2026-04-16.md": {
      "mtimeMs": 1776311183091,
      "size": 33905
    },
    "memory/2026-04-15.md": {
      "mtimeMs": 1776253584324,
      "size": 32408
    },
    "memory/2026-04-14.md": {
      "mtimeMs": 1776180602591,
      "size": 34583
    },
    "memory/2026-04-13.md": {
      "mtimeMs": 1776094202827,
      "size": 33939
    },
    "memory/2026-04-12.md": {
      "mtimeMs": 1775986202425,
      "size": 14482
    },
    "memory/2026-04-11.md": {
      "mtimeMs": 1775869217760,
      "size": 48
    },
    "memory/2026-04-10.md": {
      "mtimeMs": 1775782821748,
      "size": 83
    }
  }
}
